[{"sent_id":0,"sentence":"The Gentleman's Magazine, Vol.","file_id":"1735_a","plnames":[],"geonouns":[],"pos_words":[],"neg_words":[],"events":[],"dates":[],"times":[],"distances":[],"loc_advs":[],"spa_preps":[],"normalised_sentiment":0.0,"vader_sentiment":0.0,"roberta_sentiment":0.9950195551},{"sent_id":1,"sentence":"Xvii.","file_id":"1735_a","plnames":[],"geonouns":[],"pos_words":[],"neg_words":[],"events":[],"dates":[],"times":[],"distances":[],"loc_advs":[],"spa_preps":[],"normalised_sentiment":0.0,"vader_sentiment":0.0,"roberta_sentiment":-0.7205323577},{"sent_id":2,"sentence":"A Journey up to Cross Fell Mountain.","file_id":"1735_a","plnames":[["Cross Fell",16,26]],"geonouns":[],"pos_words":[],"neg_words":[],"events":[],"dates":[],"times":[],"distances":[],"loc_advs":[],"spa_preps":[],"normalised_sentiment":0.0,"vader_sentiment":0.0,"roberta_sentiment":0.9988002777},{"sent_id":3,"sentence":"The following account of Cross Fell will entertain such of your readers whose genius inclines them to the description of romantic scenes.","file_id":"1735_a","plnames":[["Cross Fell",25,35]],"geonouns":[],"pos_words":[["entertain",41,50],["genius",78,84],["romantic",121,129]],"neg_words":[],"events":[],"dates":[],"times":[],"distances":[],"loc_advs":[],"spa_preps":[],"normalised_sentiment":0.25,"vader_sentiment":0.61,"roberta_sentiment":0.9985598922},{"sent_id":4,"sentence":"A mountain that is generally ten months buryed in snow, and eleven in clouds, cannot fail of exciting the attention and curiosity of a traveller.","file_id":"1735_a","plnames":[],"geonouns":[["mountain",2,10]],"pos_words":[["exciting",93,101]],"neg_words":[["fail",85,89]],"events":[],"dates":[["ten months",29,39],["eleven",60,66]],"times":[],"distances":[],"loc_advs":[],"spa_preps":[],"normalised_sentiment":0.0,"vader_sentiment":0.06,"roberta_sentiment":0.9986099005},{"sent_id":5,"sentence":"That immense ridge of mountains, which are reputed the British Alps, make their first appearance in Derbyshire, and are thence continued in one chain of different elevations to the River Tweed.","file_id":"1735_a","plnames":[["Alps",63,67],["Derbyshire",100,110],["River",181,186],["Tweed",187,192]],"geonouns":[["ridge",13,18],["mountains",22,31]],"pos_words":[["immense",5,12]],"neg_words":[],"events":[],"dates":[],"times":[],"distances":[],"loc_advs":[],"spa_preps":[],"normalised_sentiment":0.0555555556,"vader_sentiment":0.0,"roberta_sentiment":0.9967106581},{"sent_id":6,"sentence":"The Lancashire and Copland heights, with those in Yorkshire and Durham, being only detached parts of this great body, such as are remarkably eminent have particular names assigned them, whilst the general ridge bears one appellation for several miles together.","file_id":"1735_a","plnames":[["Lancashire",4,14],["Copland",19,26],["Yorkshire",50,59],["Durham",64,70]],"geonouns":[["ridge",205,210]],"pos_words":[["great",106,111],["remarkably",130,140],["eminent",141,148]],"neg_words":[],"events":[],"dates":[],"times":[],"distances":[["several miles",237,250]],"loc_advs":[],"spa_preps":[["together",251,259]],"normalised_sentiment":0.1304347826,"vader_sentiment":0.66,"roberta_sentiment":0.9683985114},{"sent_id":7,"sentence":"Cross Fell, though distinguished in none of our county maps, is most singularly eminent, whether you regard its height, or the immense base it stands on, being above 20 miles in circumference; in some parts the rise is very leisurely and gradual, in others more rugged and perpendicular, emitting considerable streams to both seas.","file_id":"1735_a","plnames":[["Cross Fell",0,10]],"geonouns":[["county",48,54],["streams",310,317],["seas",326,330]],"pos_words":[["distinguished",19,32],["eminent",80,87],["regard",101,107],["immense",127,134]],"neg_words":[],"events":[],"dates":[],"times":[],"distances":[["above 20 miles",160,174]],"loc_advs":[],"spa_preps":[],"normalised_sentiment":0.1379310345,"vader_sentiment":0.0,"roberta_sentiment":0.9977678061},{"sent_id":8,"sentence":"This insensible ascent removes its top to a very great distance from the inhabited plains, and being in a manner encompassed with other desolate and barren mountains, it retains the snow much longer than any other we can see in Britain, there being some who affirm that it has continued sometimes for seven whole years together.","file_id":"1735_a","plnames":[["Britain",228,235]],"geonouns":[["mountains",156,165]],"pos_words":[["top",35,38],["great",49,54],["affirm",258,264]],"neg_words":[["insensible",5,15],["desolate",136,144],["barren",149,155]],"events":[],"dates":[["seven whole years",301,318]],"times":[],"distances":[],"loc_advs":[["there",237,242],["together",319,327]],"spa_preps":[],"normalised_sentiment":0.0,"vader_sentiment":0.73,"roberta_sentiment":-0.9987479448},{"sent_id":9,"sentence":"Aldstone is the nearest town where one can get a safe conductor to cross these almost impervious wastes, a country extremely ill represented in all our maps yet published, not to mention their exhibiting the towns on the wrong side of the river[ Nint].","file_id":"1735_a","plnames":[],"geonouns":[["town",24,28],["country",107,114],["towns",208,213],["river",239,244]],"pos_words":[["safe",49,53]],"neg_words":[["wrong",221,226]],"events":[],"dates":[],"times":[],"distances":[],"loc_advs":[],"spa_preps":[],"normalised_sentiment":0.0,"vader_sentiment":-0.51,"roberta_sentiment":-0.9668885469},{"sent_id":10,"sentence":"About two in the afternoon we set forward three in company, and two who joined us afterwards, out of the same curiosity.","file_id":"1735_a","plnames":[],"geonouns":[],"pos_words":[],"neg_words":[],"events":[],"dates":[],"times":[["the afternoon",13,26]],"distances":[],"loc_advs":[["forward",34,41]],"spa_preps":[["out",94,97]],"normalised_sentiment":0.0,"vader_sentiment":0.0,"roberta_sentiment":0.9976688027},{"sent_id":11,"sentence":"We passed the River Tine near its confluence with Blackaburn, beyond which this immense waste begins, and could plainly perceive the alteration of air in riding a few miles.","file_id":"1735_a","plnames":[["River",14,19],["Blackaburn",50,60]],"geonouns":[],"pos_words":[["immense",80,87]],"neg_words":[["waste",88,93]],"events":[],"dates":[],"times":[],"distances":[["a few miles",161,172]],"loc_advs":[["near",25,29],["beyond",62,68]],"spa_preps":[],"normalised_sentiment":0.0,"vader_sentiment":-0.42,"roberta_sentiment":-0.9988642931},{"sent_id":12,"sentence":"On the top of Roderic heights is a pretty large lake, called Green Castle-loch, which receives no visible feeder, but emits a small stream northward to the said burn; nor is there any vestige of a castle, from which it could be presumed to borrow the name.","file_id":"1735_a","plnames":[["Roderic",14,21],["Castle",67,73]],"geonouns":[["lake",48,52],["stream",132,138],["castle",197,203]],"pos_words":[["top",7,10],["pretty",35,41]],"neg_words":[["burn",161,165]],"events":[],"dates":[],"times":[],"distances":[],"loc_advs":[["northward",139,148],["there",174,179]],"spa_preps":[],"normalised_sentiment":0.0416666667,"vader_sentiment":0.23,"roberta_sentiment":-0.989076972},{"sent_id":13,"sentence":"The Swallows, those incontestable remains of Noah' s deluge, begin here to be very frequent.","file_id":"1735_a","plnames":[],"geonouns":[],"pos_words":[],"neg_words":[["deluge",53,59]],"events":[],"dates":[],"times":[],"distances":[],"loc_advs":[["here",67,71]],"spa_preps":[],"normalised_sentiment":-0.1428571429,"vader_sentiment":0.0,"roberta_sentiment":0.9852812886},{"sent_id":14,"sentence":"Some of these are 30 or 40 yards in diameter, and near as much deep, perfectly circular, but contain no water at any season, the ground having gradually fallen in at the sinking of the waters; but where they have happened amid rocks, the holes are left open to incredible depths.","file_id":"1735_a","plnames":[],"geonouns":[["water",104,109],["ground",129,135],["waters",185,191],["rocks",227,232]],"pos_words":[["perfectly",69,78],["incredible",261,271]],"neg_words":[["fallen",153,159],["sinking",170,177]],"events":[],"dates":[["30",18,20],["season",117,123]],"times":[],"distances":[],"loc_advs":[["near",50,54],["left",248,252]],"spa_preps":[["amid",222,226]],"normalised_sentiment":0.0,"vader_sentiment":-0.53,"roberta_sentiment":0.9948585033},{"sent_id":15,"sentence":"This naturally accounts for those surprizing phaenomena in the Pyrenean and Narbone mountains, and our Elden Hole in Derbyshire, whose depths have never been ascertained with the longest lines.","file_id":"1735_a","plnames":[["Pyrenean",63,71],["Narbone",76,83],["Derbyshire",117,127]],"geonouns":[["mountains",84,93],["lines",187,192]],"pos_words":[],"neg_words":[],"events":[],"dates":[],"times":[],"distances":[],"loc_advs":[],"spa_preps":[],"normalised_sentiment":0.0,"vader_sentiment":0.0,"roberta_sentiment":0.9977588654},{"sent_id":16,"sentence":"On the descent of Roderic Fell there is plenty of herbage, but few plants, save the scorpioides arvenssis, and tormentil.","file_id":"1735_a","plnames":[["Roderic",18,25]],"geonouns":[],"pos_words":[],"neg_words":[],"events":[],"dates":[],"times":[],"distances":[],"loc_advs":[["there",31,36]],"spa_preps":[],"normalised_sentiment":0.0,"vader_sentiment":0.65,"roberta_sentiment":-0.9978331923},{"sent_id":17,"sentence":"At the bottom of this height Blackaburn is divided into two branches, the eastermost tumbling over a precipice of 40 perpendicular yards, which makes a most wild, surprizing cascade.","file_id":"1735_a","plnames":[["Blackaburn",29,39]],"geonouns":[["precipice",101,110]],"pos_words":[],"neg_words":[["wild",157,161]],"events":[],"dates":[],"times":[],"distances":[],"loc_advs":[],"spa_preps":[["into",51,55],["over",94,98]],"normalised_sentiment":-0.0625,"vader_sentiment":0.0,"roberta_sentiment":0.9977091551},{"sent_id":18,"sentence":"From this rivulet we are to account the rise of Cross Fell.","file_id":"1735_a","plnames":[["Cross Fell",48,58]],"geonouns":[],"pos_words":[],"neg_words":[],"events":[],"dates":[],"times":[],"distances":[],"loc_advs":[],"spa_preps":[],"normalised_sentiment":0.0,"vader_sentiment":0.0,"roberta_sentiment":-0.9839164615},{"sent_id":19,"sentence":"We were now so much environed with large and extended morasses, rocks and mountains, that they exhibited a very frightful appearance, not the vestige of a house, except some old shiels, where in former ages the people had resorted like the Asiatic Tartars to graze their cattle in summer, a practice now quite disused.","file_id":"1735_a","plnames":[],"geonouns":[["rocks",64,69],["mountains",74,83],["house",155,160]],"pos_words":[["like",231,235]],"neg_words":[["frightful",112,121]],"events":[],"dates":[["summer",281,287]],"times":[],"distances":[],"loc_advs":[],"spa_preps":[],"normalised_sentiment":0.0,"vader_sentiment":-0.27,"roberta_sentiment":-0.9969066978},{"sent_id":20,"sentence":"There were a few sheep, but no deer, that we could see, though there are several on the heighs; and notwithstanding the extraordinary drought, the water followed our horses footsteps for miles together, except where the ground was perfectly rotten.","file_id":"1735_a","plnames":[],"geonouns":[["water",147,152],["ground",220,226]],"pos_words":[["extraordinary",120,133],["perfectly",231,240]],"neg_words":[["drought",134,141],["rotten",241,247]],"events":[],"dates":[],"times":[],"distances":[],"loc_advs":[["there",63,68]],"spa_preps":[["together",193,201]],"normalised_sentiment":0.0,"vader_sentiment":-0.12,"roberta_sentiment":0.9981796741},{"sent_id":21,"sentence":"At a place called Bulmans cleugh there have been formerly lead-works, now left off.","file_id":"1735_a","plnames":[],"geonouns":[],"pos_words":[["lead",58,62],["works",63,68]],"neg_words":[],"events":[],"dates":[],"times":[],"distances":[],"loc_advs":[["there",33,38],["left",74,78]],"spa_preps":[],"normalised_sentiment":0.2857142857,"vader_sentiment":0.0,"roberta_sentiment":-0.9890529513},{"sent_id":22,"sentence":"We had now ascended gradually about 3 miles, through very broken morassy wastes, when the mountain began to rise in three very formidable ascents, very steep, in the manner of mount Lebanon, piled one above another, with large and extensive plains to each of them, and loose shivery stones on brows, very troublesome to the horses which we now were obliged sometimes to quit.","file_id":"1735_a","plnames":[],"geonouns":[["mountain",90,98],["mount",176,181],["stones",283,289],["brows",293,298]],"pos_words":[["formidable",127,137]],"neg_words":[["broken",58,64],["steep",152,157],["loose",269,274],["troublesome",305,316]],"events":[],"dates":[],"times":[],"distances":[["about 3 miles",30,43]],"loc_advs":[["above",201,206]],"spa_preps":[["through",45,52]],"normalised_sentiment":-0.09375,"vader_sentiment":-0.85,"roberta_sentiment":-0.9878293276},{"sent_id":23,"sentence":"This continued for near 2 miles more, when we got on the edge of the highest, which forms a capacious plain of several hundred acres, if you reckon from the East ascent; but of such a barren soil, that there was not so much as a single leaf or grass, her or plant to be found in so large a plain, exclusive of a few of thoserings attributed to fairies, some of which are perfect circles of the Gramen glumis variis, in botany, ascribed by Linnaeus in his description of the Baltic isles to a particular quality of its affecting the dirtiest soil, where no other grass can thrive.","file_id":"1735_a","plnames":[],"geonouns":[["edge",57,61],["isles",481,486]],"pos_words":[["perfect",371,378],["thrive",572,578]],"neg_words":[["barren",184,190]],"events":[],"dates":[],"times":[],"distances":[["2 miles",24,31]],"loc_advs":[["near",19,23],["there",202,207]],"spa_preps":[],"normalised_sentiment":0.0208333333,"vader_sentiment":-0.05,"roberta_sentiment":-0.9985691309},{"sent_id":24,"sentence":"This immense plain has no verdure, therefore, but a venerably grey aspect from the moss or down, and even this can hardly draw a subsistence to support itself; so inconceivably barren is this distinguished eminence.","file_id":"1735_a","plnames":[],"geonouns":[],"pos_words":[["immense",5,12],["support",144,151],["distinguished",192,205],["eminence",206,214]],"neg_words":[["inconceivably",163,176],["barren",177,183]],"events":[],"dates":[],"times":[],"distances":[],"loc_advs":[],"spa_preps":[["down",91,95]],"normalised_sentiment":0.1176470588,"vader_sentiment":0.5,"roberta_sentiment":-0.9992495179},{"sent_id":25,"sentence":"The West side towards the Cumberland plains is more rocky and steep than the way we ascended.","file_id":"1735_a","plnames":[["Cumberland",26,36]],"geonouns":[],"pos_words":[],"neg_words":[["rocky",52,57],["steep",62,67]],"events":[],"dates":[],"times":[],"distances":[],"loc_advs":[],"spa_preps":[],"normalised_sentiment":-0.2222222222,"vader_sentiment":0.0,"roberta_sentiment":-0.9897202849},{"sent_id":26,"sentence":"Great part of six counties were to be seen, and notwithstanding our height, there seemed to be 4 or 5 mountains that disputed preheminence, the rest looked all far below us.","file_id":"1735_a","plnames":[],"geonouns":[["mountains",102,111]],"pos_words":[],"neg_words":[["disputed",117,125]],"events":[],"dates":[["4",95,96],["5",100,101]],"times":[],"distances":[],"loc_advs":[["there",76,81],["below",164,169]],"spa_preps":[],"normalised_sentiment":-0.0588235294,"vader_sentiment":0.4,"roberta_sentiment":0.9895451665},{"sent_id":27,"sentence":"These were Skiddow in the West of Cumberland, Criffield in Scotland, Pennygent and Ingleborough in Yorkshire, and the height Cheviot in Northumberland.","file_id":"1735_a","plnames":[["Skiddow",11,18],["Cumberland",34,44],["Criffield",46,55],["Scotland",59,67],["Pennygent",69,78],["Ingleborough",83,95],["Yorkshire",99,108],["Cheviot",125,132],["Northumberland",136,150]],"geonouns":[],"pos_words":[],"neg_words":[],"events":[],"dates":[],"times":[],"distances":[],"loc_advs":[],"spa_preps":[],"normalised_sentiment":0.0,"vader_sentiment":0.0,"roberta_sentiment":0.9975810051},{"sent_id":28,"sentence":"I computed the diameter of our visible horizon to exceed 120 miles, 60 each way from the center.","file_id":"1735_a","plnames":[],"geonouns":[["horizon",39,46]],"pos_words":[["exceed",50,56]],"neg_words":[],"events":[],"dates":[],"times":[],"distances":[["120 miles",57,66]],"loc_advs":[],"spa_preps":[],"normalised_sentiment":0.1,"vader_sentiment":0.0,"roberta_sentiment":-0.9865849018},{"sent_id":29,"sentence":"The mountains in Cleveland by the east sea were very fair, and the West sea sufficiently discoverable.","file_id":"1735_a","plnames":[["Cleveland",17,26]],"geonouns":[["mountains",4,13],["sea",39,42],["sea",72,75]],"pos_words":[["fair",53,57],["sufficiently",76,88]],"neg_words":[],"events":[],"dates":[],"times":[],"distances":[],"loc_advs":[],"spa_preps":[],"normalised_sentiment":0.2222222222,"vader_sentiment":0.38,"roberta_sentiment":0.9978316426},{"sent_id":30,"sentence":"As to the perpendicular height of the mountain, I could not so well judge, having no barometer, and the top suffers too much by refraction to be ascertained on geometrical principles.","file_id":"1735_a","plnames":[],"geonouns":[["mountain",38,46]],"pos_words":[["well",63,67],["top",104,107]],"neg_words":[["suffers",108,115]],"events":[],"dates":[],"times":[],"distances":[],"loc_advs":[],"spa_preps":[],"normalised_sentiment":0.0714285714,"vader_sentiment":-0.7,"roberta_sentiment":-0.9987541437},{"sent_id":31,"sentence":"Whether it takes its name Cross Fell from its transverse situation to the common run of that ridge, or from a papistical conjuring cross to dislodge the aerial daemons, which that region has ascribed to this desolate mountain, I take not upon me to determine.","file_id":"1735_a","plnames":[["Cross Fell",26,36]],"geonouns":[["common",74,80],["ridge",93,98],["region",180,186],["mountain",217,225]],"pos_words":[],"neg_words":[["desolate",208,216]],"events":[],"dates":[],"times":[],"distances":[],"loc_advs":[],"spa_preps":[],"normalised_sentiment":-0.0434782609,"vader_sentiment":0.0,"roberta_sentiment":-0.9642798305},{"sent_id":32,"sentence":"P. s. Being the 13th of August, and a long drought, and a hot season, we were not able to find any the least relicks of snow, in places most likely for it; which is very extraordinary.","file_id":"1735_a","plnames":[],"geonouns":[],"pos_words":[["extraordinary",170,183]],"neg_words":[["drought",43,50]],"events":[],"dates":[["the 13th of August",12,30],["a hot season",56,68]],"times":[],"distances":[],"loc_advs":[],"spa_preps":[],"normalised_sentiment":0.0,"vader_sentiment":0.0,"roberta_sentiment":-0.9878007174}]